typeworks/__init__.py
typeworks/cls_decorator_base.py
typeworks/method_decorator_base.py
typeworks/registration_decorator_base.py
typeworks/type_rgy.py
typeworks/impl/__init__.py
typeworks/impl/decl_rgy.py
typeworks/impl/method_info.py
typeworks/impl/method_proxy.py
typeworks/impl/typeinfo.py
pytypeworks-0.1.0.8548343949.dist-info/LICENSE
pytypeworks-0.1.0.8548343949.dist-info/METADATA
pytypeworks-0.1.0.8548343949.dist-info/WHEEL
pytypeworks-0.1.0.8548343949.dist-info/top_level.txt
pytypeworks-0.1.0.8548343949.dist-info/RECORD
