Metadata-Version: 2.1
Name: pytypeworks
Version: 0.1.0.8548343949
Summary: PyTypeWorks provides utilities for decorator-driven type manipulation and introspection.
Home-page: https://github.com/fvutils/pytypeworks
Author: Matthew Ballance
Author-email: matt.ballance@gmail.com
License: Apache 2.0
Keywords: Python,Decorators
License-File: LICENSE
